CHANGELOG.md
LICENSE
MANIFEST.in
README.md
setup.cfg
setup.py
pip_services3_gcp/__init__.py
pip_services3_gcp.egg-info/PKG-INFO
pip_services3_gcp.egg-info/SOURCES.txt
pip_services3_gcp.egg-info/dependency_links.txt
pip_services3_gcp.egg-info/requires.txt
pip_services3_gcp.egg-info/top_level.txt
pip_services3_gcp.egg-info/zip-safe
pip_services3_gcp/clients/CloudFunctionClient.py
pip_services3_gcp/clients/CommandableCloudFunctionClient.py
pip_services3_gcp/clients/__init__.py
pip_services3_gcp/connect/GcpConnectionParams.py
pip_services3_gcp/connect/GcpConnectionResolver.py
pip_services3_gcp/connect/__init__.py
pip_services3_gcp/containers/CloudFunction.py
pip_services3_gcp/containers/CloudFunctionRequestHelper.py
pip_services3_gcp/containers/CommandableCloudFunction.py
pip_services3_gcp/containers/__init__.py
pip_services3_gcp/services/CloudFunctionAction.py
pip_services3_gcp/services/CloudFunctionService.py
pip_services3_gcp/services/CommandableCloudFunctionService.py
pip_services3_gcp/services/ICloudFunctionService.py
pip_services3_gcp/services/__init__.py
test/clients/DummyClientFixture.py
test/clients/DummyCloudFunctionClient.py
test/clients/DummyCommandableCloudFunctionClient.py
test/clients/__init__.py
test/clients/test_DummyCloudFunctionClient.py
test/clients/test_DummyComandableCloudFunctionClient.py
test/connect/__init__.py
test/connect/test_GcpConnectionParams.py
test/containers/DummyCloudFunction.py
test/containers/DummyCloudFunctionFixture.py
test/containers/DummyCommandableCloudFunction.py
test/containers/__init__.py
test/containers/main.py
test/containers/test_DummyCommandableCloudFunction.py
test/containers/test_DummyFunctionService.py
test/services/DummyCloudFunction.py
test/services/DummyCloudFunctionFixture.py
test/services/DummyCloudFunctionService.py
test/services/DummyCommandableCloudFunction.py
test/services/DummyCommandableCloudFunctionService.py
test/services/__init__.py
test/services/main.py
test/services/test_DummyCommandableCloudFunction.py
test/services/test_DummyFunctionService.py